serialtime/__init__.py
serialtime/dataset_wrapper.py
serialtime/interactive_trying.py
serialtime/shortcuts.py
serialtime-0.1.1.dist-info/DESCRIPTION.rst
serialtime-0.1.1.dist-info/METADATA
serialtime-0.1.1.dist-info/RECORD
serialtime-0.1.1.dist-info/WHEEL
serialtime-0.1.1.dist-info/metadata.json
serialtime-0.1.1.dist-info/top_level.txt
