Metadata-Version: 2.0
Name: serialtime
Version: 0.1.1
Summary: A Python serialization tool containing many serialization and deserialization shortcuts with timing.
Home-page: https://github.com/ianlini/serialtime
Author: ianlini
Author-email: UNKNOWN
License: UNKNOWN
Platform: UNKNOWN
Classifier: Topic :: Utilities
Classifier: Programming Language :: Python :: 2.7
Classifier: Programming Language :: Python :: 3
Requires-Dist: bistiming
Requires-Dist: numpy
Requires-Dist: six
